ddh_django_utils-0.9.4.dist-info/DESCRIPTION.rst
ddh_django_utils-0.9.4.dist-info/METADATA
ddh_django_utils-0.9.4.dist-info/RECORD
ddh_django_utils-0.9.4.dist-info/WHEEL
ddh_django_utils-0.9.4.dist-info/metadata.json
ddh_django_utils-0.9.4.dist-info/pbr.json
ddh_django_utils-0.9.4.dist-info/top_level.txt
ddh_utils/__init__.py
ddh_utils/models.py
ddh_utils/utils.py
ddh_utils/views.py
ddh_utils/templates/includes/pagination.html
ddh_utils/templatetags/__init__.py
ddh_utils/templatetags/ddh_utils_tags.py
