Metadata-Version: 2.0
Name: ddh-django-utils
Version: 0.9.4
Summary: Reusable Django app containing utilities for DDH projects
Home-page: https://github.com/kcl-ddh/ddh_django_utils
Author: Jamie Norrish
Author-email: jamie@artefact.org.nz
License: Apache License, Version 2.0
Platform: UNKNOWN
Classifier: Framework :: Django
Classifier: Intended Audience :: Developers
Classifier: License :: OSI Approved :: Apache Software License
Classifier: Programming Language :: Python
Classifier: Programming Language :: Python :: 2
Classifier: Programming Language :: Python :: 2.6
Classifier: Programming Language :: Python :: 2.7
Classifier: Programming Language :: Python :: 3
Classifier: Topic :: Utilities
